odoo/addons/contract_forecast_brand/README.rst
odoo/addons/contract_forecast_brand/__init__.py
odoo/addons/contract_forecast_brand/__manifest__.py
odoo/addons/contract_forecast_brand/hooks.py
odoo/addons/contract_forecast_brand/i18n/contract_forecast_brand.pot
odoo/addons/contract_forecast_brand/i18n/it.po
odoo/addons/contract_forecast_brand/models/__init__.py
odoo/addons/contract_forecast_brand/models/contract_contract.py
odoo/addons/contract_forecast_brand/models/contract_line.py
odoo/addons/contract_forecast_brand/models/contract_line_forecast_period.py
odoo/addons/contract_forecast_brand/readme/CONTRIBUTORS.md
odoo/addons/contract_forecast_brand/readme/DESCRIPTION.md
odoo/addons/contract_forecast_brand/static/description/icon.png
odoo/addons/contract_forecast_brand/static/description/index.html
odoo/addons/contract_forecast_brand/tests/__init__.py
odoo/addons/contract_forecast_brand/tests/test_contract.py
odoo_addon_contract_forecast_brand-18.0.1.0.0.7.dist-info/METADATA
odoo_addon_contract_forecast_brand-18.0.1.0.0.7.dist-info/WHEEL
odoo_addon_contract_forecast_brand-18.0.1.0.0.7.dist-info/top_level.txt
odoo_addon_contract_forecast_brand-18.0.1.0.0.7.dist-info/RECORD
